j_chunker/__init__.py
j_chunker/chunking.py
j_chunker/embedding.py
j_chunker/llm.py
j_chunker/text_processing.py
j_chunker/utils.py
j_chunker/visualization.py
j_chunker-1.0.0.dist-info/LICENSE
j_chunker-1.0.0.dist-info/METADATA
j_chunker-1.0.0.dist-info/WHEEL
j_chunker-1.0.0.dist-info/entry_points.txt
j_chunker-1.0.0.dist-info/top_level.txt
j_chunker-1.0.0.dist-info/RECORD
