Metadata-Version: 2.1
Name: j_chunker
Version: 1.0.0
Summary: A package for chunking Japanese PDF documents
Home-page: https://github.ibm.com/shiraguppipavan/J-Chunker
Author: Pavan Shiraguppi
Author-email: Pavan Shiraguppi <shiraguppipavan@ibm.com>
License: Apache-2.0
Project-URL: homepage, https://github.ibm.com/shiraguppipavan/J-Chunker
Project-URL: source, https://github.ibm.com/shiraguppipavan/J-Chunker
Classifier: Development Status :: 3 - Alpha
Classifier: Intended Audience :: Developers
Classifier: License :: OSI Approved :: Apache Software License
Classifier: Operating System :: OS Independent
Classifier: Programming Language :: Python :: 3
Classifier: Programming Language :: Python :: 3.8
Classifier: Programming Language :: Python :: 3.9
Classifier: Programming Language :: Python :: 3.10
Requires-Python: >=3.8
License-File: LICENSE
Requires-Dist: chromadb==0.5.5
Requires-Dist: fugashi==1.3.2
Requires-Dist: Flask==3.0.3
Requires-Dist: ipadic==1.0.0
Requires-Dist: ibm-watson-machine-learning==1.0.360
Requires-Dist: Janome==0.5.0
Requires-Dist: kneed==0.8.5
Requires-Dist: langchain-ibm==0.1.11
Requires-Dist: matplotlib==3.9.1
Requires-Dist: mecab-python3==1.0.9
Requires-Dist: numpy==1.26.4
Requires-Dist: pillow==10.4.0
Requires-Dist: PyMuPDF==1.24.9
Requires-Dist: PyPDF2==3.0.1
Requires-Dist: python-dotenv==1.0.1
Requires-Dist: pytesseract==0.3.10
Requires-Dist: scikit-learn==1.5.1
Requires-Dist: sentence-transformers==3.0.1
Requires-Dist: torch==2.3.1
Requires-Dist: transformers==4.42.4
Requires-Dist: unidic-lite==1.0.8
Provides-Extra: dev
Requires-Dist: pytest; extra == "dev"
Requires-Dist: pytest-cov; extra == "dev"
Requires-Dist: flake8; extra == "dev"
Requires-Dist: black; extra == "dev"
Requires-Dist: isort; extra == "dev"
